{
    "Ar36": {
        "error": 0.0009749286162188453, 
        "filter_outliers_dict": {
            "filter_outliers": true, 
            "iterations": 2, 
            "std_devs": 2
        }, 
        "fit": "Parabolic", 
        "value": 0.24039029055709088
    }, 
    "Ar37": {
        "error": 0.011965709731592056, 
        "filter_outliers_dict": {
            "filter_outliers": true, 
            "iterations": 2, 
            "std_devs": 2
        }, 
        "fit": "linear", 
        "value": 18.239038684207504
    }, 
    "Ar38": {
        "error": 0.013649257265055467, 
        "filter_outliers_dict": {
            "filter_outliers": true, 
            "iterations": 2, 
            "std_devs": 2
        }, 
        "fit": "linear", 
        "value": 0.7116066163691794
    }, 
    "Ar39": {
        "error": 0.023652061094583066, 
        "filter_outliers_dict": {
            "filter_outliers": true, 
            "iterations": 2, 
            "std_devs": 2
        }, 
        "fit": "Parabolic", 
        "value": 16.86147976341374
    }, 
    "Ar40": {
        "error": 0.025773059906534383, 
        "filter_outliers_dict": {
            "filter_outliers": true, 
            "iterations": 2, 
            "std_devs": 2
        }, 
        "fit": "Parabolic", 
        "value": 82.35258512718374
    }
}