{
    "Ar36": {
        "error": 0.0020644365364332422, 
        "filter_outliers_dict": {
            "filter_outliers": true, 
            "iterations": 2, 
            "std_devs": 2
        }, 
        "fit": "Parabolic", 
        "value": 1.0658324474399254
    }, 
    "Ar37": {
        "error": 0.0159126132507004, 
        "filter_outliers_dict": {
            "filter_outliers": true, 
            "iterations": 2, 
            "std_devs": 2
        }, 
        "fit": "linear", 
        "value": 87.25843747890391
    }, 
    "Ar38": {
        "error": 0.01337443580112564, 
        "filter_outliers_dict": {
            "filter_outliers": true, 
            "iterations": 2, 
            "std_devs": 2
        }, 
        "fit": "linear", 
        "value": 2.7746307516156063
    }, 
    "Ar39": {
        "error": 0.02511924337985155, 
        "filter_outliers_dict": {
            "filter_outliers": true, 
            "iterations": 2, 
            "std_devs": 2
        }, 
        "fit": "Parabolic", 
        "value": 39.95925638016064
    }, 
    "Ar40": {
        "error": 0.04235936628339309, 
        "filter_outliers_dict": {
            "filter_outliers": true, 
            "iterations": 2, 
            "std_devs": 2
        }, 
        "fit": "Parabolic", 
        "value": 374.0047664169347
    }
}