{
    "Ar36": {
        "error": 0.00021090745999661424, 
        "filter_outliers_dict": {
            "filter_outliers": true, 
            "iterations": 2, 
            "std_devs": 2
        }, 
        "fit": "Parabolic", 
        "value": 0.004197794413445932
    }, 
    "Ar37": {
        "error": 0.01227179760383671, 
        "filter_outliers_dict": {
            "filter_outliers": true, 
            "iterations": 2, 
            "std_devs": 2
        }, 
        "fit": "linear", 
        "value": -0.1171838232506575
    }, 
    "Ar38": {
        "error": 0.013041370311286828, 
        "filter_outliers_dict": {
            "filter_outliers": true, 
            "iterations": 2, 
            "std_devs": 2
        }, 
        "fit": "linear", 
        "value": -0.10693928467280661
    }, 
    "Ar39": {
        "error": 0.02252492902483364, 
        "filter_outliers_dict": {
            "filter_outliers": true, 
            "iterations": 2, 
            "std_devs": 2
        }, 
        "fit": "Parabolic", 
        "value": 1.3682815906965553
    }, 
    "Ar40": {
        "error": 0.01899992194380929, 
        "filter_outliers_dict": {
            "filter_outliers": true, 
            "iterations": 2, 
            "std_devs": 2
        }, 
        "fit": "Parabolic", 
        "value": 6.359870769547755
    }
}